oneflowpy/__init__.py
oneflowpy/api/__init__.py
oneflowpy/api/api.py
oneflowpy/api/client.py
oneflowpy/api/config/__init__.py
oneflowpy/api/config/api.ini
oneflowpy/api/config/config.py
oneflowpy/api/crud.py
oneflowpy/contacts/__init__.py
oneflowpy/contacts/api.py
oneflowpy/contacts/model.py
oneflowpy/contracts/api.py
oneflowpy/contracts/model.py
oneflowpy/data_fields/api.py
oneflowpy/data_fields/model.py
oneflowpy/folders/__init__.py
oneflowpy/folders/api.py
oneflowpy/folders/model.py
oneflowpy/logs/api.py
oneflowpy/logs/model.py
oneflowpy/models/__init__.py
oneflowpy/models/core/__init__.py
oneflowpy/models/core/base_response.py
oneflowpy/models/core/permissions.py
oneflowpy/tags/__init__.py
oneflowpy/tags/api.py
oneflowpy/tags/model.py
oneflowpy/template_types/api.py
oneflowpy/template_types/model.py
oneflowpy/templates/api.py
oneflowpy/templates/model.py
oneflowpy/users/api.py
oneflowpy/users/model.py
oneflowpy/workspaces/api.py
oneflowpy/workspaces/model.py
oneflowpy-0.3.0.dist-info/METADATA
oneflowpy-0.3.0.dist-info/WHEEL
oneflowpy-0.3.0.dist-info/entry_points.txt
oneflowpy-0.3.0.dist-info/RECORD
